oscilloscopy/__init__.py
oscilloscopy/classes.py
oscilloscopy/errors.py
oscilloscopy/oscilloscopedata.py
oscilloscopy-0.1.0.dist-info/LICENSE
oscilloscopy-0.1.0.dist-info/METADATA
oscilloscopy-0.1.0.dist-info/WHEEL
oscilloscopy-0.1.0.dist-info/RECORD
