Metadata-Version: 2.1
Name: oscilloscopy
Version: 0.1.0
Summary: A Python package to parse oscilloscope data.
Home-page: https://github.com/Magmoc/oscilloscopy
License: LICENSE
Author: Erik van Weelderen
Requires-Python: >=3.12,<4.0
Classifier: License :: OSI Approved :: MIT License
Classifier: License :: Other/Proprietary License
Classifier: Operating System :: OS Independent
Classifier: Programming Language :: Python :: 3
Classifier: Programming Language :: Python :: 3.12
Classifier: Programming Language :: Python :: 3.13
Requires-Dist: pandas
Requires-Dist: pydantic
